d_flip_flop.v
module d_flip_flop (
    input wire clk,
    input wire reset,
    input wire d,
    output reg q
);

always @(posedge clk or posedge reset) begin
    if (reset)
        q <= 1'b0;
    else
        q <= d;
end

endmodule

d_flip_flop_tb.v
`timescale 1ns/1ps

module d_flip_flop_tb;

reg clk, reset, d;
wire q;

d_flip_flop dff (
    .clk(clk),
    .reset(reset),
    .d(d),
    .q(q)
);

initial begin
    clk = 0;
    forever #5 clk = ~clk;
end

initial begin
    $dumpfile("d_flip_flop.vcd");
    $dumpvars(0, d_flip_flop_tb);

    $monitor("Time=%t, clk=%b, reset=%b, d=%b, q=%b", $time, clk, reset, d, q);

    reset = 1; d = 0;
    #10 reset = 0;

    #10 d = 1;
    #10 d = 0;
    #10 d = 1;
    #10 d = 0;

    #10 reset = 1;
    #10 reset = 0;

    #10 d = 1;
    #10 d = 0;

    #10 $finish;
end

endmodule

d_flip_flop.vcd
$date
	Thu Nov 21 13:24:48 2024
$end
$version
	Icarus Verilog
$end
$timescale
	1ps
$end
$scope module d_flip_flop_tb $end
$var wire 1 ! q $end
$var reg 1 " clk $end
$var reg 1 # d $end
$var reg 1 $ reset $end
$scope module dff $end
$var wire 1 " clk $end
$var wire 1 # d $end
$var wire 1 $ reset $end
$var reg 1 ! q $end
$upscope $end
$upscope $end
$enddefinitions $end
$comment Show the parameter values. $end
$dumpall
$end
#0
$dumpvars
1$
0#
0"
0!
$end
#5000
1"
#10000
0"
0$
#15000
1"
#20000
0"
1#
#25000
1!
1"
#30000
0"
0#
#35000
0!
1"
#40000
0"
1#
#45000
1!
1"
#50000
0"
0#
#55000
0!
1"
#60000
0"
1$
#65000
1"
#70000
0"
0$
#75000
1"
#80000
0"
1#
#85000
1!
1"
#90000
0"
0#
#95000
0!
1"
