dff.v
module dff (
    input wire clk,
    input wire reset,
    input wire d,
    output reg q
);

always @(posedge clk or posedge reset) begin
    if (reset)
        q <= 1'b0;
    else
        q <= d;
end

endmodule

dff_tb.v
`timescale 1ns/1ps

module dff_tb();
    reg clk, reset, d;
    wire q;

    // Instantiate the D flip-flop
    dff dut (
        .clk(clk),
        .reset(reset),
        .d(d),
        .q(q)
    );

    // Clock generation
    always begin
        #5 clk = ~clk;
    end

    // Testbench stimulus
    initial begin
        $dumpfile("dff_tb.vcd");
        $dumpvars(0, dff_tb);

        // Initialize signals
        clk = 0;
        reset = 1;
        d = 0;

        // Release reset
        #10 reset = 0;

        // Test case 1: Set D to 1
        #10 d = 1;

        // Test case 2: Set D to 0
        #10 d = 0;

        // Test case 3: Toggle D
        #10 d = 1;
        #10 d = 0;

        // Test case 4: Assert reset
        #10 reset = 1;
        #10 reset = 0;

        // Run for a few more cycles
        #20;

        $finish;
    end

    // Display changes
    always @(posedge clk) begin
        $display("Time=%0t: reset=%b, d=%b, q=%b", $time, reset, d, q);
    end
endmodule

dff_tb.vcd
$date
	Wed Nov 20 20:29:11 2024
$end
$version
	Icarus Verilog
$end
$timescale
	1ps
$end
$scope module dff_tb $end
$var wire 1 ! q $end
$var reg 1 " clk $end
$var reg 1 # d $end
$var reg 1 $ reset $end
$scope module dut $end
$var wire 1 " clk $end
$var wire 1 # d $end
$var wire 1 $ reset $end
$var reg 1 ! q $end
$upscope $end
$upscope $end
$enddefinitions $end
$comment Show the parameter values. $end
$dumpall
$end
#0
$dumpvars
1$
0#
0"
0!
$end
#5000
1"
#10000
0"
0$
#15000
1"
#20000
0"
1#
#25000
1!
1"
#30000
0"
0#
#35000
0!
1"
#40000
0"
1#
#45000
1!
1"
#50000
0"
0#
#55000
0!
1"
#60000
0"
1$
#65000
1"
#70000
0"
0$
